{
  "id": "04tXSYmE2s",
  "name": "DJ Python (XL Recordings) & Posner /BLÅ",
  "tags": [
    "techno",
    "breakbeat",
    "house"
  ],
  "start_time": "2026-05-08T21:00:00+00:00",
  "end_time": "2026-05-09T01:00:00+00:00",
  "venue": "BLÅ",
  "description": "DJ Python (XL Recordings) & Posner\nFredag 8. mai | 23:00 | Id: 20 | cc: 180,-\nleftfield / house / breakbeat\n\nDJ Python (XL Recordings)\n\nDJ Python er hovedaliaset til Queens-baserte DJ og produsent Brian Piñeyro. En DJ av høy rang som har gode kvaliteter på tvers av sjangre og stemninger. Spilt for blant annet Dekmantel, NTS og Nuit Sonores. Han ga nylig ut EPen 'i was put on this earth' på XL Recordings.\n\nPosner\n\nOslo-basert DJ og produsent, kjent for sin ambient take på sjangre som footwork og breakbeat. Hans prosjekt 'thought this might be a good time' har blitt spilt på radioer som NTS og listet av Warp Records på deres Weekly Selections spilleliste.\n\n//\n\nDJ Python (XL Recordings)\n\nDJ Python is the main alias of Queens-based DJ and producer Brian Piñeyro. A highly regarded DJ with a strong sensibility across genres and moods, he has performed for platforms and events such as Dekmantel, NTS and Nuit Sonores. He recently released the EP i was put on this earth on XL Recordings.\n\nPosner\n\nOslo-based DJ and producer known for his ambient take on genres such as footwork and breakbeat. His project 'thought this might be a good time' has been played on radio stations across the world including NTS and was featured by Warp Records in their Weekly Selections playlist.",
  "updated_at": "2026-02-18T15:59:06.420Z",
  "ticket_url": "https://www.ticketmaster.no/event/1929771857"
}
