{
  "id": "9EFaw7GFaB",
  "name": "Fotball-VM: Finale",
  "tags": [
    "worldcup",
    "football"
  ],
  "start_time": "2026-07-19T19:00:00+02:00",
  "end_time": "2026-07-19T23:30:00+02:00",
  "venue": "Rockefeller",
  "description": "*Stort lerret - Stadionlyd - Alle rettigheter - Stor kapasitet*\n\nSe VM-finalen på Rockefeller!\n \nVi tilbyr gode fasiliteter med godt drikke, god plass og pølsesalg. Velkommen!\n\n**Dørene åpner kl. 19.00. Kampstart kl. 21.00.**\n \n--\n \nGratis inngang. 18 år leg.\n\nGjelder sitte- eller ståplass i hele lokalet etter først til mølla, bortsett fra på reserverte bord.\n\n \n**Bord-reservasjon:**\nBill. kr. 1.700,- + bill.avg. [Kjøp her](https://www.ticketmaster.no/event/1225851556) \n\n*Gjelder for 4 personer. Inkluderer sitteplass til 4 personer, snacks på bordet og 4 drikkebonger som kan brukes på alt i baren unntatt brennevin.*\n\n\n**VIP-bord:**\nBill. kr. 3.350,- + bill.avg. [Kjøp her](https://www.ticketmaster.no/event/1225851556) \n\n*Gjelder for 4 personer. Inkluderer sitteplass til 4 personer midt i salen, snacks på bordet og 8 drikkebonger som kan brukes på alt i baren.*\n\nNB! Reserverte bord frigis dersom man ikke er på plass 20 minutter før kampstart.\n\n\n18 års aldersgrense med legitimasjonsplikt. Ingen vergeordning. Gyldig legitimasjon er fysisk nasjonalt ID-kort, pass, fysisk førerkort eller bankkort med bilde. Digital legitimasjon (digitalt førerkort eller Bank-ID) eller bilde av legitimasjon er ikke gyldig legitimasjon.",
  "updated_at": "2026-07-07T09:35:51.699Z",
  "ticket_url": ""
}
