{
  "id": "B3KX3hyKfo",
  "name": "Time-Space-Continuum",
  "tags": [
    "Jazz,",
    "Impro,"
  ],
  "start_time": "2026-04-19T20:00:00+02:00",
  "end_time": "2026-04-19T23:00:00+02:00",
  "venue": "KAFÉ HÆRVERK",
  "description": "Juliana Venter selected four world class musicians for a new quartet called Time-Space-Continuum. \n\nA group of musicians that have embraced all styles of music yet each one of them have their own individual sound frequenting stages around the globe. \n\nVenter has made a name on the Norwegian scene with duo Nystrøm/Venter, Paal Nilssen-Love circus , Janne Eraker ensemble, and more recently with “ It was her idea” ( Grönberg/ Morten Vågan/Nilssen- Love) \n\nShe has also been co-curator of the award winning Fram kunstfestivalen on Nesodden for the past six years. As an actress she has spend the past 9 years collaborating with theatre group Det Utvalgte on various productions. She will  be releasing a solo vocal album on Sonic Transmissions- 10/02/2026.\n\nPianist and composer Jonas Cambien works in free jazz, improvisation, world music and contemporary classical music. His quartet Maca Conu with (Emmeluth/Flaten/Wildhagen) received rave reviews. Furthermore he collaborates and performs internationally with Kairo based trio - The Handover; Oslo based- Majãz (with musicians from Syria, Palestine and Norway)   Aksiom; Simiskina ; and more. \n\n Bass player and composer Ingebrigt Håker Flaten recently voted one of the most important innovators on the bass worldwide, ( Downbeat) is known for his work in many styles of music such as free jazz , modern jazz, rock, experimental music and hiphop. He is known for his work with Atomic, The Thing, The Young Mothers and Exit ( Knarr).\n\nDrummer and Composer Kesivan Naidoo from South Africa is a multi award winning drummer known as one of the greatest drummer of his generation. Born into the so-called Y Generation, a “freedom’s children” that got to celebrate the liberation their parents fought so hard for, Kesivan was always conscious of the need to forge a new musical identity.\n\n For Kesivan sound is rooted in improvisation, in rapturous expression and radical invention – but most importantly in listening.\n\nHaving played with Miriam Makeba and Louis Moholo Moholo , Feya Faku and many more. Kesivan and the Lights is his current big band . \n\nOn April the 19th \n\nTSC will be performing at legendary Kafe Haerverk in Oslo. \n\nBased and inspired by South African , European and Norwegian jazz , world music and contemporary classical music.  \n\nMusic as a form of resistance ,friction, an outcry for rebellion a celebration of life , a voice to the marginalized, a call to freedom. \n\n",
  "updated_at": "2026-04-13T20:35:22.180Z",
  "ticket_url": "https://tikkio.com/events/56695"
}
