{
  "id": "ctAYeghHua",
  "name": "Shapednoise (IT) & Chosen1",
  "tags": [
    "techno",
    "experimental",
    "industrial"
  ],
  "start_time": "2026-08-01T23:00:00+02:00",
  "end_time": "2026-08-02T03:00:00+02:00",
  "venue": "BLÅ",
  "description": "Shapednoise is the project of Berlin-based, Sicilian-born producer, DJ, and sound artist Nino Pedone. Known for blending industrial textures, experimental electronics, hardcore, hip-hop, and club music, he has developed a distinctive sound that pushes genre boundaries. He has released music on labels including Opal Tapes, Type, Numbers, and his own WEIGHT LOOMING, and has performed at leading festivals such as Berlin Atonal, CTM, Unsound, and Club To Club.\n\nThe Oslo-based experimental producer and guitarist is involved in projects even beyond our knowledge, most recently releasing the self-titled debut album with his band Skitne Kroner on Borgenheim Rosenhoff. Alongside his solo and band outputs he has for years built up a reputation for his mind-bending DJ-sets.",
  "updated_at": "2026-07-20T14:46:37.719Z",
  "ticket_url": "https://www.ticketmaster.no/event/1683883675"
}
