{
  "id": "FQlTUV7PJ9",
  "name": "Strange Dolls // Acoustic Live",
  "tags": [
    "Rock",
    "Acoustic",
    "Rocknroll"
  ],
  "start_time": "2026-06-04T20:00:00+02:00",
  "end_time": "2026-06-04T22:00:00+02:00",
  "venue": "Brewgata",
  "description": "Elegantly Wasted & Perfectly Out Of Tune\n- The reunion of the year -\n\n19 years after Glamour Punks legends Trashcan Darlings disbanded, Chris Damien Doll and Strange? Gentle have once again decided to come together... over you.\n\nStrangeDolls will perform some of their most beautiful songs acoustically at Brew Gata on June 4th, just the two of them, like at all those backstage parties in the past. The songs are just as full of raw emotions today as they ever were and... who knows if it will take another 19 years for this chance to come again...  \n\n\nThis is the StrangeDolls:\n\nBorn from the glitter of the gutters in the pouring rain. Playing music for lovers and haters out there in the night. Songs of hearts and roses, stories of dreams and desires, distorted pasts and futures that never came, tales of kings & queens, untuned guitars and desolate streets. The StrangeDolls were there, lived there, almost died there, but survived and have returned to tell their story.\n\nYou remember them, you say? Like a glimpse of a broken dream from a time when the future used to look better? A distorted remembrance of one of those late, drunken, nights in a time that is no more, but always was, and always will be… Cause it’s true, my love. It’s true.\nThere was a time...\n\nThe StrangeDolls coloured those graveyards of lost hope in colours without names. You could see them walking down the alleys, dressed to kill. They had so much style... In a way you feel you knew them, you loved them, you lost them.\n\nThere was a time... that time is now\n\nThe StrangeDolls are Strange? Gentle & Chris Damien Doll",
  "updated_at": "2026-06-01T08:46:53.012Z",
  "ticket_url": "https://tikkio.com/events/63430"
}
