{
  "id": "Gb3CxbhJus",
  "name": "Brewgata x Inferno Matinée // AUTOMATON Live",
  "tags": [
    "doom",
    "metal",
    "inferno"
  ],
  "start_time": "2026-04-03T15:00:00+02:00",
  "end_time": "2026-04-03T16:00:00+02:00",
  "venue": "Brewgata",
  "description": "Cavern Deep is a slow, heavy band, founded 2019, by members from Zonaria and Swedish retro riffsters Gudars Skymning. The band released its first self-titled concept album through Interstellar Smoke Records and then went on to form their own record label called Bonebag Records, releasing their second album \"Part II - Breach\" to critical acclaim.\n\nTheir latest album “Part III - The Bodiless” is set to release the 9th of May 2025. It is the final entry in the concept album trilogy started with their debut album released in 2021. \n\nFree Entry with Festival Pass\n250 nok Door for non festival\n\n20. yo",
  "updated_at": "2026-04-02T15:09:18.301Z",
  "ticket_url": ""
}
