{
  "id": "iBYl3GYGFZ",
  "name": "Tunage: Dunder / Patman / Branko 808 ",
  "tags": [
    "jungle",
    "dnb"
  ],
  "start_time": "2026-01-24T22:00:00+00:00",
  "end_time": "2026-01-25T02:29:00+00:00",
  "venue": "KAFÉ HÆRVERK",
  "description": "Tunage is celebration of electronic music on vinyl, with a special focus on jungle, hardcore & dnb. From old to new with a generous twist and particular vibe. Started by Branko 808 in 2024 Tunage has been serving quality beats for two years.\nDJ Branko 808 is from former Czechoslovakia. He likes synthesizers and all things electronic. Being the father of Tunage, Branko plays mostly jungle, hardcore, DNB and minimal music. T shirt size XXL, boots 46😊\nDj Dunder is a figurehead in the rave scene from way back in the days. Dunder did his first gig in 1999 and he is a self proclaimed music freak living for quality breaks and amens. A vinyl fanatic at heart he has love for\nJungle & Drum ‘n’ Bass.\nT-shirt size L, shoes 43,1/3\nPatman, a specialist in UK hardcore, Jungle, Drum ‘n Bass and Bleeps, he is also an enthusiastic collector of all things breakbeat, bass music and beyond..\nCollecting physical formats since the 90s and playing the first gigs in 2000. XXL T-shirt\nShoe size 44 to the floor watch out for this hot steppa\n--\nID: 20\nCC: 120,-",
  "updated_at": "2026-01-04T14:36:55.259Z",
  "ticket_url": ""
}
