{
  "id": "NGi70AU4Qj",
  "name": "Tarja ",
  "tags": [
    "symphonicmetal",
    "heavymetal"
  ],
  "start_time": "2027-02-18T19:00:00+01:00",
  "end_time": "2027-02-18T23:00:00+01:00",
  "venue": "Rockefeller",
  "description": "Etter den massive og kritikerroste konserten på Tons of Rock 2025 vender endelig Tarja tilbake til Norge med sin helt nye turné: «Frisson Live 2027». Torsdag 18. februar er hun klar for Rockefeller!\n\nTarja regnes som en av de mest definerende stemmene innen symfonisk- og heavy metal, og fikk først internasjonal anerkjennelse som grunnlegger og frontvokalist i Nightwish. Som klassisk utdannet sopran kombinerte hun operateknikk med metal og skapte en helt ny sound som fortsatt inspirerer generasjoner av artister den dag i dag. Gjennom ikoniske album og verdensomspennende turneer var hun med på å forme en hel æra innen symfonisk metal og la grunnlaget for en helt ekstraordinær karriere.\n\nParallelt med denne turneen slipper Tarja sitt splitter nye studioalbum – hennes første fullengder i en tyngre musikalsk retning på syv år. \n\n«Frisson» beskriver øyeblikket når musikken sender frysninger nedover ryggraden. Når følelsene treffer uventet. Når energien strømmer gjennom hele kroppen. Akkurat den følelsen står i sentrum for denne turneen. Kraftfulle og dynamiske spenningskurver – fra intime og skjøre øyeblikk til eksplosive refrenger, og en settliste som kombinerer helt nytt materiale med karrieredefinerende høydepunkter.\n\n--\n \nBill. kr. 545,- + bill.avg.\n \n18 års aldersgrense med legitimasjonsplikt. Ingen vergeordning. Gyldig legitimasjon er fysisk nasjonalt ID-kort, pass, fysisk førerkort eller bankkort med bilde. Digital legitimasjon (digitalt førerkort eller Bank-ID) eller bilde av legitimasjon er ikke gyldig legitimasjon.\n \nArrangementer har ståplasser.\n \nDørene åpner kl. 19.00. Arrangementet starter ca. 1 time etter dørene åpner. NB! Det anbefales å komme i god tid før arrangementet starter da det kan bli kø.",
  "updated_at": "2026-05-28T13:59:16.868Z",
  "ticket_url": "https://www.ticketmaster.no/event/194887206?brand=rockefeller&camefrom=CFC_NO_Rockefeller_Tarja_180227_Billettsalg&utm_campaign=NO_Rockefeller_Tarja_180227_Billettsalg&utm_content=NO&utm_medium=referral&utm_source=Website"
}
