{
  "id": "oEjQXRYfzK",
  "name": "The Devil and the Almighty Blues",
  "tags": [
    "bluesrock",
    "hardrock"
  ],
  "start_time": "2026-10-28T19:00:00+01:00",
  "end_time": "2026-10-28T23:00:00+01:00",
  "venue": "John Dee",
  "description": "The Devil and the Almighty Blues kommer til John Dee onsdag 28. oktober!\n\nMed base i Oslo siden 2010 har The Devil and the Almighty Blues for lengst skapt seg et navn helt på egne premisser. Deres dype respekt for de klassiske bluesheltene smelter sømløst sammen med rock, metal, country – og en subtil dose punk.\n\nTungt, seigt, melodisk og rått – men alltid med røttene godt plantet i den mektige bluesen. Tungt uten å bli metal. Langsomt uten å gli over i doom. Dynket i blues uten noen gang å høres utdatert ut.\n\nDe er aktuelle med den nye singelen «Lied To».\n\n--\n \nBill. kr. 310,- + bill.avg.\n \n18 års aldersgrense med legitimasjonsplikt. Ingen vergeordning. Gyldig legitimasjon er fysisk nasjonalt ID-kort, pass, fysisk førerkort eller bankkort med bilde. Digital legitimasjon (digitalt førerkort eller Bank-ID) eller bilde av legitimasjon er ikke gyldig legitimasjon.\n \nArrangementet har ståplasser.\n \nDørene åpner kl. 19.00. Arrangementet starter ca. 1 time etter dørene åpner. NB! Det anbefales å komme i god tid før arrangementet starter da det kan bli kø.",
  "updated_at": "2026-06-18T09:29:08.333Z",
  "ticket_url": "https://www.ticketmaster.no/event/1421417765?brand=johndee&camefrom=CFC_NO_Rockefeller%2BSentrum%2BScene%2BJohn%2BDee_The_Devil_and_the_Almighty_Blues_281026_Billettsalg&utm_campaign=NO_Rockefeller%2BSentrum%2BScene%2BJohn%2BDee_The_Devil_and_the_Almighty_Blues_281026_Billettsalg&utm_content=NO&utm_medium=referral&utm_source=Website"
}
