{
  "id": "RpWyd0rKv9",
  "name": "Tinie Tempah",
  "tags": [
    "Rap",
    "Grime",
    "UK hip-hop"
  ],
  "start_time": "2026-11-18T20:00:00+01:00",
  "end_time": "2026-11-18T23:00:00+01:00",
  "venue": "Vulkan Arena",
  "description": "Tinie Tempah returnerer til Norge\nDen britiske hitmakeren Tinie Tempah kommer endelig tilbake til Norge! Onsdag 18. november inntar han Vulkan Arena, klar for et etterlengtet gjensyn med sitt norske publikum.\n\nTinie Tempah slo for alvor gjennom i 2010 med debutsingelen «Pass Out», som gikk rett til topps på den britiske singellisten. Kort tid etter fulgte «Frisky» og den internasjonale kjempehiten «Written in the Stars», og med debutalbumet Disc-Overy etablerte han seg som en av de største britiske artistene innen rap, pop og elektronisk musikk.\n\nSiden gjennombruddet har Tinie Tempah levert en lang rekke globale hits, toppet de britiske listene flere ganger og samarbeidet med noen av verdens største artister og produsenter. Dette har gitt oss låter som «Miami 2 Ibiza» med Swedish House Mafia, «Not Letting Go» med Jess Glynne, «Girls Like» med Zara Larsson og «Drinking from the Bottle» med Calvin Harris.\nDen britiske stjernen har også en lang historie i Norge. Fra å ha spilt på landets største konsertscener og headlinet flere store festivaler, har han gjennom årene opparbeidet seg et sterkt forhold til sitt norske publikum.\n\nNå er Tinie Tempah endelig tilbake med ny musikk og et nytt album er på vei! Samtidig returnerer han endelig til Oslo, denne gangen til Vulkan Arena. Publikum kan vente seg en kveld fylt med store hits, nye låter og energien som har gjort ham til en av Storbritannias største liveartister.\nBilletter i salg fredag 17. juli kl. 10.00 via ticketmaster.no\n\nOrdinær: https://www.ticketmaster.no/event/97595072\nVIP: https://www.ticketmaster.no/event/474576236\n\n*VIP-ticket includes:* \n- GA ticket\n- M&G with Tinie (pre-show)                      \n- Individual photo with Tinie (photo taken on your own phone)\n- Early access to merch stand",
  "updated_at": "2026-07-13T10:12:20.686Z",
  "ticket_url": "https://www.ticketmaster.no/artist/tinie-tempah-billetter/341013?utm_source=broadcast&utm_medium=referral&utm_campaign=broadcast_api&utm_content=ticket"
}
