{
  "id": "S6JY0DpHGC",
  "name": "Fredfades (Mutual Intentions, Tøyen Holding) invites Anacalypto (GR/NL) /BLÅ",
  "tags": [
    "techno",
    "house",
    "trance"
  ],
  "start_time": "2026-01-17T22:00:00+00:00",
  "end_time": "2026-01-18T02:00:00+00:00",
  "venue": "BLÅ",
  "description": "Fredfades (Mutual Intentions, Tøyen Holding) invites Anacalypto (GR/NL)\nLørdag 17. Januar | 23:00 | Id: 20\ntechno / house / trance / breakbeat\n\nTil tross for at de knapt har møttes i virkeligheten (med kun et unntak over en middag i Berlin) møtes Fredfades og Anacalypto bak platespillerne for første gang, etter flere år som internettvenner med nokså parallelle reiser i klubbmusikkens mer obskure landskaper.\nDe har fulgt hverandres mikser, samlinger og utgivelser, med en felles forståelse for gammel klubbmusikk, uten å være drevet av nostalgi. For begge to handler det om en nysgjerrighet og en dragning mot ukjente og uavhengige perler innen klubbmusikk som fortsatt låter relevant, selv flere tiår etter sin slippdato.\n\nSjangermessig vil kvelden bevege seg gjennom balearic house, deep house, acid, techno, breakbeats, ambient house, dub techno og progressive house, trance og mye mer.\n\nVi sees på BLÅ!",
  "updated_at": "2026-01-05T15:52:05.781Z",
  "ticket_url": "https://www.ticketmaster.no/event/1994310244"
}
