{
  "id": "SszLV2akMH",
  "name": "SKJULTE SKATTER #41: NOCTURBULOUS FUNK DISSOCIATION VOL. 3 // Kafé Hærverk ",
  "tags": [
    "Electro,  experimental,  techno"
  ],
  "start_time": "2026-03-17T21:00:00+00:00",
  "end_time": "2026-03-18T02:15:00+00:00",
  "venue": "KAFÉ HÆRVERK",
  "description": "Elektronisk og eksperimentelt med Baldee og L.I.T.S.W.D.\n\nKanskje kommer også Ramy\n\nHer er et opptak av Baldee og L.I.T.S.W.D. fra Baldees program Konseptronika på RadiOrakel:\n\nhttps://on.soundcloud.com/4h10YIr31hu0ceg1tp\n\nID: 20\nCC: Gratis\n\nSkjulte Skatter på SoundCloud:\nhttps://on.soundcloud.com/qsNSNEnNIBXhEs5YmL\n",
  "updated_at": "2026-03-13T12:04:40.951Z",
  "ticket_url": ""
}
