{
  "id": "vwUiw8jUMr",
  "name": "High on Fire",
  "tags": [
    "metal",
    "stoner",
    "sludge"
  ],
  "start_time": "2026-08-20T17:00:00+00:00",
  "end_time": "2026-08-20T21:00:00+00:00",
  "venue": "Rockefeller",
  "description": "Den Grammy-vinnende powertrioen High on Fire kommer endelig tilbake til Oslo! Vi har ikke hatt bandet på besøk hos oss siden en utsolgt konsert på John Dee i 2013, så nå var det virkelig på tide med et gjensyn – denne gangen på selveste Rockefeller!\n\nHigh on Fire har vært en tung og kompromissløs kraft siden oppstarten i 1998. Med en egenartet miks av primal aggresjon og monumentale riff har de sikret seg en plass blant de mest slagkraftige metalbandene i vår tid. \n\nFrontfigur Matt Pike har selv påpekt at High on Fire ikke er for alle, og definitivt ikke for kommersiell radio. Dette er musikk for de innvidde, for et publikum som verdsetter et kompromissløst og særegent uttrykk. Foreløpig siste album, *Cometh the Storm*, ble utgitt i 2024.\n\n--\n \nBill. kr. 395,- + bill.avg.\n \n18 års aldersgrense med legitimasjonsplikt. Ingen vergeordning. Gyldig legitimasjon er fysisk nasjonalt ID-kort, pass, fysisk førerkort eller bankkort med bilde. Digital legitimasjon (digitalt førerkort eller Bank-ID) eller bilde av legitimasjon er ikke gyldig legitimasjon.\n \nArrangementer har ståplasser.\n \nDørene åpner kl. 19.00. Arrangementet starter ca. 1 time etter dørene åpner. NB! Det anbefales å komme i god tid før arrangementet starter da det kan bli kø.",
  "updated_at": "2026-02-02T10:01:18.507Z",
  "ticket_url": "https://www.ticketmaster.no/event/794004853?brand=rockefeller&camefrom=CFC_NO_Rockefeller_High_On_Fire_200826_Billettsalg&utm_campaign=NO_Rockefeller_High_On_Fire_200826_Billettsalg&utm_content=NO&utm_medium=referral&utm_source=Website"
}
