{
  "id": "XmBAE4uXDQ",
  "name": "Nektar + Special guest: 1991",
  "tags": [
    "indie",
    "rock",
    "alternative"
  ],
  "start_time": "2026-10-14T19:00:00+02:00",
  "end_time": "2026-10-14T23:00:00+02:00",
  "venue": "BLÅ",
  "description": "Med debutalbumet Magnolia og singler som «Sitt Ner (Lilla Jag)» og «Älskar Dig (Oändligt Föralltid)» etablerte Nektar seg på rekordtid som et av Sveriges mest hyllede og omtalte band. Göteborg-bandet ble raskt en selvsagt del av den svenske indierockscenen og bygget opp en fanskare med en hengivenhet og lojalitet som er uvanlig i dag. Siden starten i begynnelsen av 2024 har Nektar solgt ut konserter over hele landet, blitt kåret til Årets Gjennombrudd av GAFFA og fått stor ros fra Fredrik Strage – både i Nyhetsmorgon og i podkasten Hemma hos Strage.\n\n1991 er et høylytt bergensbasert band med røtter i Sunnfjord, som beveger seg selvsikkert i landskapet mellom poprock, alt-rock og grunge. Bandet kombinerer nonchalant rock med høye gitarer, og ærlige, melankolske tekster. Gikk du glipp av storhetstiden til giganter som Oasis, Weezer, Smashing Pumpkins, og Pixies, kan du nå gjenoppleve følelsen nå, gjennom stemmen til frontmann Torkel Eikevik. Bandet ga i April ut sin selvtitulerte debut på Apollon Records, produsert av ingen ringere enn Robert Jønnum (Kristi Brud) og stjerneprodusent Odd-Martin Skålnes. \n ",
  "updated_at": "2026-06-24T08:00:12.950Z",
  "ticket_url": "https://www.ticketmaster.no/event/999926588"
}
