{
  "id": "zZDOCUNzp1",
  "name": "Moonwraith + Edvard Sundquist",
  "tags": [
    "Stoner, doom,"
  ],
  "start_time": "2026-04-01T18:00:00+00:00",
  "end_time": "2026-04-01T21:00:00+00:00",
  "venue": "KAFÉ HÆRVERK",
  "description": "Moonwraith er et stonerrock band fra Oslo. De har bygd seg et godt rykte som live band, og har spilt på scener som Desertfest og Musikkens dag i Oslo. Fram til nå har det meste av musikken deres bare blitt hørt av folk som har sett dem live — låtene har levd sitt eget liv på scenen før de har blitt sluppet offisielt. Nå slipper de endelig innspilt musikk, så alle også kan høre hvordan bandet låter på plate.\n\nEdvard Sundquist\nDen elektriske gitaren nærmer seg 100 år og begynner å opparbeide seg en rimelig solid musikalsk arv. Men kan den også fungere som et klassisk instrument på samme nivå som hvilket som helst annet akustisk instrument? For å besvare det spørsmålet har gitarist Edvard Sundquist arrangert sonatene og partitaene for solo fiolin av J.S. Bach for elgitar. Selv om musikken en veldig tro mot de orginale partiturer, er arrangementene og spillistilen også inspirert av en rekke forskjellige kilder. Filtrert gjennom lyden av Keith Richards og Jimmy Page til mer moderne gitarister som Marc Ribot, Julian Lage og Bill Frisell, er resultatet et heksebrygg av de siste 300 årene. Den første sonaten og den første partitaen ble i høst spilt inn i Ormøy kirke med Øyvind Blomstrøm som produsent og kommer ut som et album høsten 2026",
  "updated_at": "2026-03-18T13:13:38.275Z",
  "ticket_url": "https://tikkio.com/events/61818"
}
